contributions/__init__.py
contributions/__main__.py
contributions/config.py
contributions/git.py
contributions/utils.py
contributions/fonts/KeepCalm-Medium.py
contributions/fonts/__init__.py
contributions/fonts/arial.py
contributions-0.1.0.dist-info/METADATA
contributions-0.1.0.dist-info/RECORD
contributions-0.1.0.dist-info/WHEEL
contributions-0.1.0.dist-info/entry_points.txt
contributions-0.1.0.dist-info/pbr.json
contributions-0.1.0.dist-info/top_level.txt
